edupress/__init__.py
edupress/base.html
edupress/footer.html
edupress/header.html
edupress/home.html
edupress/main.html
edupress/mkdocs_theme.yml
edupress/post.html
edupress/rtl.css
edupress/sidebar.html
edupress/style.css
edupress/urls.json
edupress/css/editor-style.css
edupress/css/social.css
edupress/js/customizer.js
edupress/js/edupress.js
edupress/js/jquery.flexslider.js
edupress/js/jquery.slicknav.js
edupress/js/jquery.slicknav.min.js
edupress/js/rss.js
edupress/js/superfish.js
edupress/js/superfish.min.js
mkdocs_edupress_theme-0.0.1.dist-info/METADATA
mkdocs_edupress_theme-0.0.1.dist-info/WHEEL
mkdocs_edupress_theme-0.0.1.dist-info/entry_points.txt
mkdocs_edupress_theme-0.0.1.dist-info/top_level.txt
mkdocs_edupress_theme-0.0.1.dist-info/RECORD
