Metadata-Version: 2.1
Name: mkdocs-edupress-theme
Version: 0.0.1
Summary: Edupress theme for mkdocs
Home-page: https://github.com/kubilus1/mkdocs-edupress-theme
Author: Matt Kubilus
Author-email: mattkubilus@gmail.com
License: GPL
Platform: UNKNOWN
Requires-Dist: mkdocs-datesort-plugin (>=0.0.2)
Requires-Dist: mkdocs-paginate-plugin (>=0.0.4)
Requires-Dist: mkdocs (>=0.17)
